{"type":"View","props":{"width":750,"top":0,"right":0,"left":0,"height":1334,"bottom":0},"compId":2,"child":[{"type":"Box","props":{"top":0,"right":0,"name":"bg","left":0,"bottom":0,"bgColor":"#313131","alpha":0.5},"compId":3},{"type":"Image","props":{"x":375,"width":411,"top":50,"skin":"Over/win_title.min.png","scaleY":1,"scaleX":1,"pivotY":79,"pivotX":206,"name":"title","height":157},"compId":4},{"type":"Script","props":{"runtime":"MyScripts/View/OverView.ts"},"compId":8},{"type":"Button","props":{"stateNum":1,"skin":"Over/12_0047_按钮-拷贝.png","name":"btn_continue","centerX":0,"bottom":350},"compId":9,"child":[{"type":"Image","props":{"y":27,"x":80},"compId":10,"child":[{"type":"Text","props":{"y":4,"x":-25,"text":"Continue","fontSize":33,"font":"Microsoft YaHei","color":"#ffffff","bold":true,"runtime":"Laya.Text"},"compId":48}]}]},{"type":"Button","props":{"x":0,"width":150,"stateNum":1,"skin":"Menu/12_0035_组-34.png","name":"btn_sideAD","left":-28,"height":113,"bottom":320},"compId":26,"child":[{"type":"Sprite","props":{"y":27,"x":72,"width":38,"texture":"Menu/12_0000_图层-512.png","height":54},"compId":27}]},{"type":"Button","props":{"width":262,"stateNum":1,"skin":"Over/12_0047_按钮-拷贝.png","scaleY":1,"scaleX":1,"name":"btn_openTreasure","height":112,"centerX":0,"bottom":325},"compId":6,"child":[{"type":"Image","props":{"y":27,"x":57,"width":148,"height":42},"compId":7,"child":[{"type":"Text","props":{"y":1,"x":-10,"text":"Treasure","fontSize":40,"color":"#ffffff","bold":true,"runtime":"Laya.Text"},"compId":49}]},{"type":"Sprite","props":{"y":6,"x":19,"width":224,"name":"kuan","mouseEnabled":false,"height":82,"drawCallOptimize":true},"compId":22,"child":[{"type":"Script","props":{"right_x":164,"left_x":-150,"runtime":"MyScripts/Ctrl/ButtonShan.ts"},"compId":23},{"type":"Sprite","props":{"y":-5,"x":-146,"width":216,"texture":"Common/shang.png","name":"shan","height":91},"compId":24}]},{"type":"Script","props":{"y":0,"x":0,"press":true,"runtime":"Common/MyButton.ts"},"compId":45}]},{"type":"Image","props":{"skin":"Rank/level5.png","pivotY":139,"pivotX":131,"name":"cup","centerY":-420,"centerX":0},"compId":28,"child":[{"type":"Image","props":{"y":291,"skin":"Rank/condition0.png","name":"condition","centerX":0},"compId":29},{"type":"Image","props":{"y":0,"width":260,"scaleY":1.4,"scaleX":1.4,"pivotX":1,"name":"stars","centerX":-2},"compId":31,"child":[{"type":"Sprite","props":{"y":-48,"x":3},"compId":32,"child":[{"type":"Sprite","props":{"y":30,"x":-0.75,"width":36,"texture":"Rank/icon_star02.min.png","name":"star0","height":37},"compId":33},{"type":"Sprite","props":{"y":11,"x":50.25,"width":36,"texture":"Rank/icon_star02.min.png","name":"star1","height":37},"compId":34},{"type":"Sprite","props":{"x":107.25,"width":36,"texture":"Rank/icon_star02.min.png","name":"star2","height":37},"compId":35},{"type":"Sprite","props":{"y":11,"x":167.25,"width":36,"texture":"Rank/icon_star02.min.png","name":"star3","height":37},"compId":36},{"type":"Sprite","props":{"y":30,"x":215.25,"width":36,"texture":"Rank/icon_star02.min.png","name":"star4","height":37},"compId":37}]},{"type":"Sprite","props":{"y":1,"x":21,"width":36,"texture":"Rank/icon_star.min.png","pivotY":19,"pivotX":18,"name":"star0","height":37},"compId":38},{"type":"Sprite","props":{"y":-18,"x":71,"width":36,"texture":"Rank/icon_star.min.png","pivotY":19,"pivotX":18,"name":"star1","height":37},"compId":39},{"type":"Sprite","props":{"y":-29,"x":128,"width":36,"texture":"Rank/icon_star.min.png","pivotY":19,"pivotX":18,"name":"star2","height":37},"compId":40},{"type":"Sprite","props":{"y":-18,"x":188,"width":36,"texture":"Rank/icon_star.min.png","pivotY":19,"pivotX":18,"name":"star3","height":37},"compId":41},{"type":"Sprite","props":{"y":1,"x":236,"width":36,"texture":"Rank/icon_star.min.png","pivotY":19,"pivotX":18,"name":"star4","height":37},"compId":42}]},{"type":"Script","props":{"runtime":"MyScripts/Ctrl/OverCup.ts"},"compId":43}]}],"loadList":["Over/win_title.min.png","Over/12_0047_按钮-拷贝.png","Menu/12_0035_组-34.png","Menu/12_0000_图层-512.png","Common/shang.png","Rank/level5.png","Rank/condition0.png","Rank/icon_star02.min.png","Rank/icon_star.min.png"],"loadList3D":[]}